{"cookies": [{"name": "JSESSIONID", "value": "0C1E730B2D0A7E4D7B197284A65CE167.mono-web-prod_202.38", "domain": "www.encar.com", "path": "/", "expires": -1, "httpOnly": false, "secure": false, "sameSite": "Lax"}, {"name": "WMONID", "value": "Vn23rmQbrnU", "domain": "www.encar.com", "path": "/", "expires": 1789588115.780977, "httpOnly": false, "secure": false, "sameSite": "Lax"}, {"name": "OAX", "value": "d0LgUmjJQIgABqcQ", "domain": ".encar.com", "path": "/", "expires": 1792579715.832998, "httpOnly": false, "secure": false, "sameSite": "Lax"}, {"name": "_encar_hostname", "value": "https://www.encar.com", "domain": ".encar.com", "path": "/", "expires": 1758106115, "httpOnly": false, "secure": false, "sameSite": "Lax"}, {"name": "_fwb", "value": "687a2gGdCATkRwJfEgTkAo.1758019716115", "domain": ".encar.com", "path": "/", "expires": 1792579716.11592, "httpOnly": false, "secure": false, "sameSite": "Lax"}, {"name": "wcs_bt", "value": "4b4e532670e38c:1758019716", "domain": "www.encar.com", "path": "/", "expires": 1792579716.117672, "httpOnly": false, "secure": false, "sameSite": "Lax"}, {"name": "NWB", "value": "b38a048f5bb98f095279de675c4e38da.1758019721098", "domain": ".wcs.naver.com", "path": "/", "expires": 1792579716.134569, "httpOnly": false, "secure": true, "sameSite": "None"}, {"name": "NAC", "value": "8tOBBwwjSPSt", "domain": ".naver.com", "path": "/", "expires": 1792579716.175542, "httpOnly": false, "secure": true, "sameSite": "None"}, {"name": "test_cookie", "value": "CheckForPermission", "domain": ".doubleclick.net", "path": "/", "expires": 1758020616.276899, "httpOnly": false, "secure": true, "sameSite": "None"}, {"name": "PCID", "value": "17580197163373303772938", "domain": ".encar.com", "path": "/", "expires": 1792579716.337776, "httpOnly": false, "secure": false, "sameSite": "Lax"}, {"name": "_enlog_lpi", "value": "fdf4.aHR0cHM6Ly93d3cuZW5jYXIuY29tL2luZGV4LmRv.258", "domain": ".encar.com", "path": "/", "expires": 1758021516, "httpOnly": false, "secure": false, "sameSite": "Lax"}, {"name": "_ga", "value": "GA1.2.42157071.1758019716", "domain": ".encar.com", "path": "/", "expires": 1792579716.49653, "httpOnly": false, "secure": false, "sameSite": "Lax"}, {"name": "_gid", "value": "GA1.2.788575870.1758019716", "domain": ".encar.com", "path": "/", "expires": 1758106116, "httpOnly": false, "secure": false, "sameSite": "Lax"}, {"name": "_gat_UA-56065139-3", "value": "1", "domain": ".encar.com", "path": "/", "expires": 1758019776, "httpOnly": false, "secure": false, "sameSite": "Lax"}, {"name": "_fbp", "value": "fb.1.1758019716683.911846729598693892", "domain": ".encar.com", "path": "/", "expires": 1765795716, "httpOnly": false, "secure": false, "sameSite": "Lax"}, {"name": "_ga_WY0RWR65ED", "value": "GS2.2.s1758019716$o1$g0$t1758019716$j60$l0$h0", "domain": ".encar.com", "path": "/", "expires": 1792579716.859573, "httpOnly": false, "secure": false, "sameSite": "Lax"}], "origins": [{"origin": "https://www.encar.com", "localStorage": [{"name": "NACT", "value": "1758019716177"}, {"name": "NAC", "value": "8tOBBwwjSPSt"}, {"name": "lastExternalReferrerTime", "value": "1758019716674"}, {"name": "lastExternalReferrer", "value": "empty"}, {"name": "aws.cognito.identity-id.ap-northeast-2:7fbb4026-7b49-4ca4-a93e-bfae7bf48d3d", "value": "ap-northeast-2:4803ab9a-5eea-ce43-de43-39df6cf54f89"}, {"name": "NA_NACC", "value": "8tOBBwwjSPSt"}]}]}